sample_designs/sync_fifo_dir/sync_fifo.sv
module sync_fifo #(
    parameter DATA_WIDTH = 8,
    parameter DEPTH = 4
) (
    input  logic                  clk,
    input  logic                  rst_n,
    input  logic                  wr_en,
    input  logic                  rd_en,
    input  logic [DATA_WIDTH-1:0] din,
    output logic [DATA_WIDTH-1:0] dout,
    output logic                  full,
    output logic                  empty
);

    localparam ADDR_WIDTH = $clog2(DEPTH);

    logic [DATA_WIDTH-1:0] fifo [0:DEPTH-1];
    logic [ADDR_WIDTH:0]   wr_ptr, rd_ptr;
    logic                  fifo_full, fifo_empty;

    // Write logic
    always_ff @(posedge clk or negedge rst_n) begin
        if (!rst_n) begin
            wr_ptr <= '0;
        end else if (wr_en && !fifo_full) begin
            fifo[wr_ptr[ADDR_WIDTH-1:0]] <= din;
            wr_ptr <= wr_ptr + 2; //Purposely faulty
        end
    end

    // Read logic
    always_ff @(posedge clk or negedge rst_n) begin
        if (!rst_n) begin
            rd_ptr <= '0;
            dout   <= '0;
        end else if (rd_en && !fifo_empty) begin
            dout   <= fifo[rd_ptr[ADDR_WIDTH-1:0]];
            rd_ptr <= rd_ptr + 1;
        end
    end

    // Status flags
    assign fifo_full  = (wr_ptr - rd_ptr) == DEPTH;
    assign fifo_empty = (wr_ptr == rd_ptr);
    assign full       = fifo_full;
    assign empty      = fifo_empty;
    

endmodule

sample_designs/sync_fifo_dir/dump.vcd
$version Generated by VerilatedVcd $end
$timescale 1ps $end
 $scope module $rootio $end
  $var wire 1 # clk $end
  $var wire 1 $ rst_n $end
  $var wire 1 % wr_en $end
  $var wire 1 & rd_en $end
  $var wire 8 ' din [7:0] $end
  $var wire 8 ( dout [7:0] $end
  $var wire 1 ) full $end
  $var wire 1 * empty $end
 $upscope $end
 $scope module sync_fifo $end
  $var wire 32 ; DATA_WIDTH [31:0] $end
  $var wire 32 < DEPTH [31:0] $end
  $var wire 1 + clk $end
  $var wire 1 , rst_n $end
  $var wire 1 - wr_en $end
  $var wire 1 . rd_en $end
  $var wire 8 / din [7:0] $end
  $var wire 8 0 dout [7:0] $end
  $var wire 1 1 full $end
  $var wire 1 2 empty $end
  $var wire 32 = ADDR_WIDTH [31:0] $end
  $var wire 8 3 fifo[0] [7:0] $end
  $var wire 8 4 fifo[1] [7:0] $end
  $var wire 8 5 fifo[2] [7:0] $end
  $var wire 8 6 fifo[3] [7:0] $end
  $var wire 3 7 wr_ptr [2:0] $end
  $var wire 3 8 rd_ptr [2:0] $end
  $var wire 1 9 fifo_full $end
  $var wire 1 : fifo_empty $end
 $upscope $end
$enddefinitions $end


#0
1#
0$
0%
0&
b00000000 '
b00000000 (
0)
1*
1+
0,
0-
0.
b00000000 /
b00000000 0
01
12
b00000000 3
b00000000 4
b00000000 5
b00000000 6
b000 7
b000 8
09
1:
b00000000000000000000000000001000 ;
b00000000000000000000000000000100 <
b00000000000000000000000000000010 =
#5
0#
1$
0+
1,
#10
1#
1+
#15
0#
1%
b00000001 '
0+
1-
b00000001 /
#20
1#
0*
1+
02
b00000001 3
b010 7
0:
#25
0#
b00000010 '
0+
b00000010 /
#30
1#
1)
1+
11
b00000010 5
b100 7
19
#35
0#
b00000011 '
0+
b00000011 /
#40
1#
1+
#45
0#
b00000100 '
0+
b00000100 /
#50
1#
1+
#55
0#
0%
1&
0+
0-
1.
#60
1#
b00000001 (
0)
1+
b00000001 0
01
b001 8
09
#65
0#
0+
#70
1#
b00000000 (
1+
b00000000 0
b010 8
#75
0#
0+
#80
1#
b00000010 (
1+
b00000010 0
b011 8
#85
0#
0+
#90
1#
b00000000 (
1*
1+
b00000000 0
12
b100 8
1:
#95
0#
0&
0+
0.
